zip2tz/__init__.py
zip2tz/_data.py
zip2tz/py.typed
zip2tz-0.1.2.dist-info/METADATA
zip2tz-0.1.2.dist-info/WHEEL
zip2tz-0.1.2.dist-info/licenses/LICENSE
zip2tz-0.1.2.dist-info/RECORD
