Metadata-Version: 2.4
Name: zip2tz
Version: 0.1.2
Summary: A simple timezone lookup by zip code
Author-email: kylehogate <kyle.holgate@gmail.com>
License-File: LICENSE
Requires-Python: >=3.9
